<annotation>
	<folder>waldo</folder>
	<filename>18_0_3.jpg</filename>
	<path>D:\projects\python\vision2020\research\wheres-waldo\Hey-Waldo\256\waldo\18_0_3.jpg</path>
	<source>
		<database>Unknown</database>
	</source>
	<size>
		<width>256</width>
		<height>256</height>
		<depth>3</depth>
	</size>
	<segmented>0</segmented>
	<object>
		<name>waldo</name>
		<pose>Unspecified</pose>
		<truncated>0</truncated>
		<difficult>0</difficult>
		<bndbox>
			<xmin>118</xmin>
			<ymin>170</ymin>
			<xmax>168</xmax>
			<ymax>241</ymax>
		</bndbox>
	</object>
</annotation>
